lps28.py
circuitpython_lps28-0.1.1.dist-info/LICENSE
circuitpython_lps28-0.1.1.dist-info/METADATA
circuitpython_lps28-0.1.1.dist-info/WHEEL
circuitpython_lps28-0.1.1.dist-info/top_level.txt
circuitpython_lps28-0.1.1.dist-info/RECORD
